odoo/addons/partner_name_hide_parent/README.rst
odoo/addons/partner_name_hide_parent/__init__.py
odoo/addons/partner_name_hide_parent/__manifest__.py
odoo/addons/partner_name_hide_parent/i18n/es.po
odoo/addons/partner_name_hide_parent/i18n/ja.po
odoo/addons/partner_name_hide_parent/i18n/partner_name_hide_parent.pot
odoo/addons/partner_name_hide_parent/models/__init__.py
odoo/addons/partner_name_hide_parent/models/res_partner.py
odoo/addons/partner_name_hide_parent/readme/DESCRIPTION.rst
odoo/addons/partner_name_hide_parent/readme/USAGE.rst
odoo/addons/partner_name_hide_parent/static/description/icon.png
odoo/addons/partner_name_hide_parent/static/description/index.html
odoo/addons/partner_name_hide_parent/tests/__init__.py
odoo/addons/partner_name_hide_parent/tests/test_partner_name_hide_parent.py
odoo/addons/partner_name_hide_parent/views/res_partner_views.xml
odoo_addon_partner_name_hide_parent-15.0.1.0.0.6.dist-info/METADATA
odoo_addon_partner_name_hide_parent-15.0.1.0.0.6.dist-info/WHEEL
odoo_addon_partner_name_hide_parent-15.0.1.0.0.6.dist-info/top_level.txt
odoo_addon_partner_name_hide_parent-15.0.1.0.0.6.dist-info/RECORD
